odoo10_addon_procurement_auto_create_group-10.0.1.0.0-py2.7-nspkg.pth
odoo/addons/procurement_auto_create_group/README.rst
odoo/addons/procurement_auto_create_group/__init__.py
odoo/addons/procurement_auto_create_group/__manifest__.py
odoo/addons/procurement_auto_create_group/i18n/de.po
odoo/addons/procurement_auto_create_group/i18n/es.po
odoo/addons/procurement_auto_create_group/i18n/es_MX.po
odoo/addons/procurement_auto_create_group/i18n/fr.po
odoo/addons/procurement_auto_create_group/i18n/hr.po
odoo/addons/procurement_auto_create_group/i18n/it.po
odoo/addons/procurement_auto_create_group/i18n/pt_BR.po
odoo/addons/procurement_auto_create_group/i18n/pt_PT.po
odoo/addons/procurement_auto_create_group/i18n/ro.po
odoo/addons/procurement_auto_create_group/i18n/sk.po
odoo/addons/procurement_auto_create_group/i18n/sl.po
odoo/addons/procurement_auto_create_group/i18n/tr_TR.po
odoo/addons/procurement_auto_create_group/i18n/vi_VN.po
odoo/addons/procurement_auto_create_group/i18n/zh_CN.po
odoo/addons/procurement_auto_create_group/models/__init__.py
odoo/addons/procurement_auto_create_group/models/procurement.py
odoo/addons/procurement_auto_create_group/models/procurement_rule.py
odoo/addons/procurement_auto_create_group/static/description/icon.png
odoo/addons/procurement_auto_create_group/tests/__init__.py
odoo/addons/procurement_auto_create_group/tests/test_auto_create.py
odoo/addons/procurement_auto_create_group/views/procurement_view.xml
odoo10_addon_procurement_auto_create_group-10.0.1.0.0.dist-info/DESCRIPTION.rst
odoo10_addon_procurement_auto_create_group-10.0.1.0.0.dist-info/METADATA
odoo10_addon_procurement_auto_create_group-10.0.1.0.0.dist-info/RECORD
odoo10_addon_procurement_auto_create_group-10.0.1.0.0.dist-info/WHEEL
odoo10_addon_procurement_auto_create_group-10.0.1.0.0.dist-info/metadata.json
odoo10_addon_procurement_auto_create_group-10.0.1.0.0.dist-info/namespace_packages.txt
odoo10_addon_procurement_auto_create_group-10.0.1.0.0.dist-info/top_level.txt
